pubweb/__init__.py
pubweb/file_utils.py
pubweb/utils.py
pubweb/api/__init__.py
pubweb/api/config.py
pubweb/api/auth/__init__.py
pubweb/api/auth/base.py
pubweb/api/auth/iam.py
pubweb/api/auth/oauth_client.py
pubweb/api/auth/username.py
pubweb/api/clients/__init__.py
pubweb/api/clients/api.py
pubweb/api/clients/portal.py
pubweb/api/clients/s3.py
pubweb/api/clients/utils.py
pubweb/api/models/__init__.py
pubweb/api/models/api.py
pubweb/api/models/auth.py
pubweb/api/models/dataset.py
pubweb/api/models/exceptions.py
pubweb/api/models/file.py
pubweb/api/models/form_specification.py
pubweb/api/models/process.py
pubweb/api/models/project.py
pubweb/api/models/reference.py
pubweb/api/models/s3_path.py
pubweb/api/models/workflow_models.py
pubweb/api/services/__init__.py
pubweb/api/services/base.py
pubweb/api/services/common.py
pubweb/api/services/dataset.py
pubweb/api/services/file.py
pubweb/api/services/process.py
pubweb/api/services/project.py
pubweb/cli/__init__.py
pubweb/cli/cli.py
pubweb/cli/controller.py
pubweb/cli/models.py
pubweb/cli/interactive/__init__.py
pubweb/cli/interactive/auth_args.py
pubweb/cli/interactive/common_args.py
pubweb/cli/interactive/download_args.py
pubweb/cli/interactive/list_dataset_args.py
pubweb/cli/interactive/upload_args.py
pubweb/cli/interactive/utils.py
pubweb/cli/interactive/workflow_args.py
pubweb/cli/interactive/workflow_form_args.py
pubweb/helpers/__init__.py
pubweb/helpers/constants.py
pubweb/helpers/form.py
pubweb/helpers/preprocess_dataset.py
pubweb/helpers/workflow_config.py
pubweb/sdk/__init__.py
pubweb/sdk/asset.py
pubweb/sdk/dataset.py
pubweb/sdk/exceptions.py
pubweb/sdk/file.py
pubweb/sdk/helpers.py
pubweb/sdk/portal.py
pubweb/sdk/process.py
pubweb/sdk/project.py
pubweb/sdk/reference.py
pubweb/sdk/reference_type.py
pubweb-0.5.0.dist-info/LICENSE.txt
pubweb-0.5.0.dist-info/METADATA
pubweb-0.5.0.dist-info/WHEEL
pubweb-0.5.0.dist-info/entry_points.txt
pubweb-0.5.0.dist-info/top_level.txt
pubweb-0.5.0.dist-info/RECORD
