Metadata-Version: 2.1
Name: pubweb
Version: 0.5.0
Summary: CLI tool for interacting with the PubWeb platform
Home-page: https://github.com/FredHutch/PubWeb-client
Author: Fred Hutch
Author-email: hutchdatacore@fredhutch.org
License: MIT
Platform: UNKNOWN
Requires-Dist: click (>=8.1.3)
Requires-Dist: boto3 (==1.*)
Requires-Dist: botocore (==1.*)
Requires-Dist: questionary (>=1.10.0)
Requires-Dist: gql[requests] (>=3.4.0)
Requires-Dist: requests (>=2.28.1)
Requires-Dist: requests-aws4auth (>=1.1.2)
Requires-Dist: pycognito (>=2022.8.0)
Requires-Dist: tqdm (>=4.62.3)
Requires-Dist: pandas (>=1.5.0)
Requires-Dist: pygithub (>=1.56)
Requires-Dist: jsonschema (>=4.6.1)
Requires-Dist: s3fs (==0.4.*)
Requires-Dist: fsspec (==2022.*)
Requires-Dist: pyjwt (==2.4.0)
Requires-Dist: msal-extensions (==1.0.0)
